evmdasm/__init__.py
evmdasm/__main__.py
evmdasm/argtypes.py
evmdasm/disassembler.py
evmdasm/instruction_registry.py
evmdasm/instructions.py
evmdasm/registry.py
evmdasm/utils.py
evmdasm/xx.py
evmdasm-0.1.8.dist-info/METADATA
evmdasm-0.1.8.dist-info/WHEEL
evmdasm-0.1.8.dist-info/top_level.txt
evmdasm-0.1.8.dist-info/RECORD
