Metadata-Version: 2.1
Name: evmdasm
Version: 0.1.8
Summary: A lightweight ethereum evm bytecode asm instruction registry and disassembler library.
Home-page: https://github.com/tintinweb/evmdasm
Author: tintinweb
Author-email: tintinweb@oststrom.com
License: GPLv2
Download-URL: https://github.com/tintinweb/evmdasm/tarball/v0.1.8
Keywords: evmdasm,ethereum,blockchain,evm,disassembler
Platform: UNKNOWN
